freewheel/__init__.py
freewheel/errors.py
pyfreewheel-0.1.0.dist-info/COPYING
pyfreewheel-0.1.0.dist-info/METADATA
pyfreewheel-0.1.0.dist-info/WHEEL
pyfreewheel-0.1.0.dist-info/top_level.txt
pyfreewheel-0.1.0.dist-info/RECORD
