Metadata-Version: 2.1
Name: pyfreewheel
Version: 0.1.0
Summary: Communicate with the Freewheel inbound API
Home-page: https://github.com/entrez/pyfreewheel
Author: Michael Meyer
Author-email: me@entrez.cc
License: UNKNOWN
Keywords: api freewheel adtech
Platform: UNKNOWN
Classifier: Programming Language :: Python :: 3
Classifier: License :: OSI Approved :: GNU General Public License v3 or later (GPLv3+)
Classifier: Operating System :: OS Independent
Classifier: Intended Audience :: Developers
Classifier: Development Status :: 3 - Alpha
Classifier: Programming Language :: Python :: 3.5
Classifier: Programming Language :: Python :: 3.6
Classifier: Programming Language :: Python :: 3.7
Requires-Python: >=3.5
